zipcoil/__init__.py
zipcoil/agent.py
zipcoil/core.py
zipcoil/py.typed
zipcoil/types.py
zipcoil-0.2.1.dist-info/licenses/LICENSE
zipcoil-0.2.1.dist-info/METADATA
zipcoil-0.2.1.dist-info/WHEEL
zipcoil-0.2.1.dist-info/top_level.txt
zipcoil-0.2.1.dist-info/RECORD
