Metadata-Version: 2.4
Name: zipcoil
Version: 0.2.1
Summary: Zipcoil simplifies OpenAI tool usage
Author: Vlad Iliescu
License-Expression: LGPL-3.0
Project-URL: Homepage, https://github.com/vladiliescu/zipcoil
Project-URL: Repository, https://github.com/vladiliescu/zipcoil
Keywords: openai,tools,ai
Classifier: Development Status :: 3 - Alpha
Classifier: Intended Audience :: Developers
Classifier: Programming Language :: Python :: 3
Classifier: Programming Language :: Python :: 3.11
Classifier: Programming Language :: Python :: 3.12
Classifier: Typing :: Typed
Requires-Python: >=3.11
License-File: LICENSE
Requires-Dist: openai>=1.0.0
Requires-Dist: docstring-parser>=0.16
Dynamic: license-file
